watermarker/__init__.py
watermarker/command_line.py
watermarker_Darkclainer-1.0.0.dist-info/LICENSE
watermarker_Darkclainer-1.0.0.dist-info/METADATA
watermarker_Darkclainer-1.0.0.dist-info/WHEEL
watermarker_Darkclainer-1.0.0.dist-info/entry_points.txt
watermarker_Darkclainer-1.0.0.dist-info/top_level.txt
watermarker_Darkclainer-1.0.0.dist-info/RECORD
