Metadata-Version: 2.1
Name: watermarker-Darkclainer
Version: 1.0.0
Summary: Small utility to watermark your images with a text
Home-page: https://github.com/darkclainer/watermarker
Author: Darkclainer
Author-email: Darkclainer@gmail.com
License: UNKNOWN
Project-URL: Bug Tracker, https://github.com/darkclainer/watermarker/issues
Platform: UNKNOWN
Classifier: Programming Language :: Python :: 3
Classifier: License :: OSI Approved :: MIT License
Classifier: Operating System :: OS Independent
Requires-Python: >=3.6
Requires-Dist: Pillow (>=8.0.0)
